xevent/__init__.py
xevent/composite.py
xevent-0.4.dist-info/METADATA
xevent-0.4.dist-info/WHEEL
xevent-0.4.dist-info/top_level.txt
xevent-0.4.dist-info/RECORD
